markdown_exec-1.12.1.dist-info/METADATA
markdown_exec-1.12.1.dist-info/WHEEL
markdown_exec-1.12.1.dist-info/entry_points.txt
markdown_exec-1.12.1.dist-info/licenses/LICENSE
markdown_exec/__init__.py
markdown_exec/_internal/__init__.py
markdown_exec/_internal/debug.py
markdown_exec/_internal/formatters/__init__.py
markdown_exec/_internal/formatters/_exec_python.py
markdown_exec/_internal/formatters/base.py
markdown_exec/_internal/formatters/bash.py
markdown_exec/_internal/formatters/console.py
markdown_exec/_internal/formatters/markdown.py
markdown_exec/_internal/formatters/pycon.py
markdown_exec/_internal/formatters/pyodide.py
markdown_exec/_internal/formatters/python.py
markdown_exec/_internal/formatters/sh.py
markdown_exec/_internal/formatters/tree.py
markdown_exec/_internal/logger.py
markdown_exec/_internal/main.py
markdown_exec/_internal/mkdocs_plugin.py
markdown_exec/_internal/processors.py
markdown_exec/_internal/rendering.py
markdown_exec/assets/ansi.css
markdown_exec/assets/pyodide.css
markdown_exec/assets/pyodide.js
markdown_exec/formatters/__init__.py
markdown_exec/formatters/base.py
markdown_exec/formatters/bash.py
markdown_exec/formatters/console.py
markdown_exec/formatters/markdown.py
markdown_exec/formatters/pycon.py
markdown_exec/formatters/pyodide.py
markdown_exec/formatters/python.py
markdown_exec/formatters/sh.py
markdown_exec/formatters/tree.py
markdown_exec/logger.py
markdown_exec/mkdocs_plugin.py
markdown_exec/processors.py
markdown_exec/py.typed
markdown_exec/rendering.py
markdown_exec-1.12.1.dist-info/RECORD
