Metadata-Version: 2.4
Name: markdown-exec
Version: 1.12.1
Summary: Utilities to execute code blocks in Markdown files.
Keywords: markdown,python,exec,shell,bash,mkdocs
Author-Email: =?utf-8?q?Timoth=C3=A9e_Mazzucotelli?= <dev@pawamoy.fr>
License-Expression: ISC
License-File: LICENSE
Classifier: Development Status :: 4 - Beta
Classifier: Intended Audience :: Developers
Classifier: Programming Language :: Python
Classifier: Programming Language :: Python :: 3
Classifier: Programming Language :: Python :: 3 :: Only
Classifier: Programming Language :: Python :: 3.10
Classifier: Programming Language :: Python :: 3.11
Classifier: Programming Language :: Python :: 3.12
Classifier: Programming Language :: Python :: 3.13
Classifier: Programming Language :: Python :: 3.14
Classifier: Topic :: Documentation
Classifier: Topic :: Software Development
Classifier: Topic :: Utilities
Classifier: Typing :: Typed
Project-URL: Homepage, https://pawamoy.github.io/markdown-exec
Project-URL: Documentation, https://pawamoy.github.io/markdown-exec
Project-URL: Changelog, https://pawamoy.github.io/markdown-exec/changelog
Project-URL: Repository, https://github.com/pawamoy/markdown-exec
Project-URL: Issues, https://github.com/pawamoy/markdown-exec/issues
Project-URL: Discussions, https://github.com/pawamoy/markdown-exec/discussions
Project-URL: Gitter, https://gitter.im/markdown-exec/community
Project-URL: Funding, https://github.com/sponsors/pawamoy
Requires-Python: >=3.10
Requires-Dist: pymdown-extensions>=9
Provides-Extra: ansi
Requires-Dist: pygments-ansi-color>=0.3; extra == "ansi"
